<?xml version="1.0"?>
  <Table>
   <Row>
    <Cell>4113</Cell>
    <Cell>1</Cell>
    <Cell>5</Cell>
    <Cell>1</Cell>
   </Row>
   <Row>
    <Cell>4114</Cell>
    <Cell>1</Cell>
    <Cell>5</Cell>
    <Cell>1</Cell>
   </Row>
   <Row>
    <Cell>4115</Cell>
    <Cell>1</Cell>
    <Cell>5</Cell>
    <Cell>1</Cell>
   </Row>
   <Row>
    <Cell>4116</Cell>
    <Cell>1</Cell>
    <Cell>5</Cell>
    <Cell>1</Cell>
   </Row>
   <Row>
    <Cell>4117</Cell>
    <Cell>1</Cell>
    <Cell>5</Cell>
    <Cell>1</Cell>
   </Row>
   <Row>
    <Cell>4118</Cell>
    <Cell>1</Cell>
    <Cell>5</Cell>
    <Cell>1</Cell>
   </Row>
   <Row>
    <Cell>4119</Cell>
    <Cell>1</Cell>
    <Cell>5</Cell>
    <Cell>1</Cell>
   </Row>
   <Row>
    <Cell>4120</Cell>
    <Cell>1</Cell>
    <Cell>5</Cell>
    <Cell>1</Cell>
   </Row>
   <Row>
    <Cell>4121</Cell>
    <Cell>1</Cell>
    <Cell>5</Cell>
    <Cell>1</Cell>
   </Row>
   <Row>
    <Cell>4122</Cell>
    <Cell>1</Cell>
    <Cell>5</Cell>
    <Cell>1</Cell>
   </Row>
   <Row>
    <Cell>4123</Cell>
    <Cell>1</Cell>
    <Cell>5</Cell>
    <Cell>1</Cell>
   </Row>
   <Row>
    <Cell>4124</Cell>
    <Cell>1</Cell>
    <Cell>5</Cell>
    <Cell>1</Cell>
   </Row>
   <Row>
    <Cell>4125</Cell>
    <Cell>1</Cell>
    <Cell>5</Cell>
    <Cell>1</Cell>
   </Row>
   <Row>
    <Cell>4126</Cell>
    <Cell>1</Cell>
    <Cell>5</Cell>
    <Cell>1</Cell>
   </Row>
   <Row>
    <Cell>4127</Cell>
    <Cell>1</Cell>
    <Cell>5</Cell>
    <Cell>1</Cell>
   </Row>
   <Row>
    <Cell>4128</Cell>
    <Cell>1</Cell>
    <Cell>5</Cell>
    <Cell>1</Cell>
   </Row>
   <Row>
    <Cell>4129</Cell>
    <Cell>1</Cell>
    <Cell>5</Cell>
    <Cell>1</Cell>
   </Row>
   <Row>
    <Cell>4130</Cell>
    <Cell>1</Cell>
    <Cell>5</Cell>
    <Cell>1</Cell>
   </Row>
   <Row>
    <Cell>4131</Cell>
    <Cell>1</Cell>
    <Cell>5</Cell>
    <Cell>1</Cell>
   </Row>
   <Row>
    <Cell>4132</Cell>
    <Cell>1</Cell>
    <Cell>5</Cell>
    <Cell>1</Cell>
   </Row>
   <Row>
    <Cell>4133</Cell>
    <Cell>1</Cell>
    <Cell>5</Cell>
    <Cell>1</Cell>
   </Row>
   <Row>
    <Cell>4134</Cell>
    <Cell>1</Cell>
    <Cell>5</Cell>
    <Cell>1</Cell>
   </Row>
   <Row>
    <Cell>4135</Cell>
    <Cell>1</Cell>
    <Cell>5</Cell>
    <Cell>1</Cell>
   </Row>
   <Row>
    <Cell>4136</Cell>
    <Cell>1</Cell>
    <Cell>5</Cell>
    <Cell>1</Cell>
   </Row>
   <Row>
    <Cell>4137</Cell>
    <Cell>1</Cell>
    <Cell>5</Cell>
    <Cell>1</Cell>
   </Row>
   <Row>
    <Cell>4138</Cell>
    <Cell>1</Cell>
    <Cell>5</Cell>
    <Cell>1</Cell>
   </Row>
   <Row>
    <Cell>4139</Cell>
    <Cell>1</Cell>
    <Cell>5</Cell>
    <Cell>1</Cell>
   </Row>
   <Row>
    <Cell>4140</Cell>
    <Cell>1</Cell>
    <Cell>5</Cell>
    <Cell>1</Cell>
   </Row>
   <Row>
    <Cell>4141</Cell>
    <Cell>1</Cell>
    <Cell>5</Cell>
    <Cell>1</Cell>
   </Row>
   <Row>
    <Cell>4142</Cell>
    <Cell>1</Cell>
    <Cell>5</Cell>
    <Cell>1</Cell>
   </Row>
   <Row>
    <Cell>4143</Cell>
    <Cell>1</Cell>
    <Cell>5</Cell>
    <Cell>1</Cell>
   </Row>
   <Row>
    <Cell>4144</Cell>
    <Cell>1</Cell>
    <Cell>5</Cell>
    <Cell>1</Cell>
   </Row>
   <Row>
    <Cell>4145</Cell>
    <Cell>1</Cell>
    <Cell>5</Cell>
    <Cell>1</Cell>
   </Row>
   <Row>
    <Cell>4146</Cell>
    <Cell>1</Cell>
    <Cell>5</Cell>
    <Cell>1</Cell>
   </Row>
   <Row>
    <Cell>4147</Cell>
    <Cell>1</Cell>
    <Cell>5</Cell>
    <Cell>1</Cell>
   </Row>
   <Row>
    <Cell>4148</Cell>
    <Cell>1</Cell>
    <Cell>5</Cell>
    <Cell>1</Cell>
   </Row>
   <Row>
    <Cell>4149</Cell>
    <Cell>1</Cell>
    <Cell>5</Cell>
    <Cell>1</Cell>
   </Row>
   <Row>
    <Cell>4150</Cell>
    <Cell>1</Cell>
    <Cell>5</Cell>
    <Cell>1</Cell>
   </Row>
   <Row>
    <Cell>4151</Cell>
    <Cell>1</Cell>
    <Cell>5</Cell>
    <Cell>1</Cell>
   </Row>
   <Row>
    <Cell>4152</Cell>
    <Cell>1</Cell>
    <Cell>5</Cell>
    <Cell>1</Cell>
   </Row>
   <Row>
    <Cell>4153</Cell>
    <Cell>1</Cell>
    <Cell>5</Cell>
    <Cell>1</Cell>
   </Row>
   <Row>
    <Cell>4154</Cell>
    <Cell>1</Cell>
    <Cell>5</Cell>
    <Cell>1</Cell>
   </Row>
   <Row>
    <Cell>4155</Cell>
    <Cell>1</Cell>
    <Cell>5</Cell>
    <Cell>1</Cell>
   </Row>
   <Row>
    <Cell>4156</Cell>
    <Cell>1</Cell>
    <Cell>5</Cell>
    <Cell>1</Cell>
   </Row>
   <Row>
    <Cell>4157</Cell>
    <Cell>1</Cell>
    <Cell>5</Cell>
    <Cell>1</Cell>
   </Row>
   <Row>
    <Cell>4331</Cell>
    <Cell>1</Cell>
    <Cell>2</Cell>
    <Cell>1</Cell>
   </Row>
   <Row>
    <Cell>4332</Cell>
    <Cell>1</Cell>
    <Cell>2</Cell>
    <Cell>1</Cell>
   </Row>
   <Row>
    <Cell>4333</Cell>
    <Cell>1</Cell>
    <Cell>2</Cell>
    <Cell>1</Cell>
   </Row>
   <Row>
    <Cell>4334</Cell>
    <Cell>1</Cell>
    <Cell>2</Cell>
    <Cell>1</Cell>
   </Row>
   <Row>
    <Cell>4335</Cell>
    <Cell>1</Cell>
    <Cell>2</Cell>
    <Cell>1</Cell>
   </Row>
   <Row>
    <Cell>4336</Cell>
    <Cell>1</Cell>
    <Cell>2</Cell>
    <Cell>1</Cell>
   </Row>
   <Row>
    <Cell>4337</Cell>
    <Cell>1</Cell>
    <Cell>2</Cell>
    <Cell>1</Cell>
   </Row>
   <Row>
    <Cell>4338</Cell>
    <Cell>1</Cell>
    <Cell>2</Cell>
    <Cell>1</Cell>
   </Row>
   <Row>
    <Cell>4339</Cell>
    <Cell>1</Cell>
    <Cell>2</Cell>
    <Cell>1</Cell>
   </Row>
   <Row>
    <Cell>4340</Cell>
    <Cell>1</Cell>
    <Cell>2</Cell>
    <Cell>1</Cell>
   </Row>
   <Row>
    <Cell>4341</Cell>
    <Cell>1</Cell>
    <Cell>2</Cell>
    <Cell>1</Cell>
   </Row>
   <Row>
    <Cell>4342</Cell>
    <Cell>1</Cell>
    <Cell>2</Cell>
    <Cell>1</Cell>
   </Row>
   <Row>
    <Cell>4343</Cell>
    <Cell>1</Cell>
    <Cell>2</Cell>
    <Cell>1</Cell>
   </Row>
   <Row>
    <Cell>4344</Cell>
    <Cell>1</Cell>
    <Cell>2</Cell>
    <Cell>1</Cell>
   </Row>
   <Row>
    <Cell>4345</Cell>
    <Cell>1</Cell>
    <Cell>2</Cell>
    <Cell>1</Cell>
   </Row>
   <Row>
    <Cell>4346</Cell>
    <Cell>1</Cell>
    <Cell>2</Cell>
    <Cell>1</Cell>
   </Row>
   <Row>
    <Cell>4347</Cell>
    <Cell>1</Cell>
    <Cell>2</Cell>
    <Cell>1</Cell>
   </Row>
   <Row>
    <Cell>4348</Cell>
    <Cell>1</Cell>
    <Cell>2</Cell>
    <Cell>1</Cell>
   </Row>
   <Row>
    <Cell>4349</Cell>
    <Cell>1</Cell>
    <Cell>2</Cell>
    <Cell>1</Cell>
   </Row>
   <Row>
    <Cell>4350</Cell>
    <Cell>1</Cell>
    <Cell>2</Cell>
    <Cell>1</Cell>
   </Row>
   <Row>
    <Cell>4351</Cell>
    <Cell>1</Cell>
    <Cell>2</Cell>
    <Cell>1</Cell>
   </Row>
   <Row>
    <Cell>4352</Cell>
    <Cell>1</Cell>
    <Cell>2</Cell>
    <Cell>1</Cell>
   </Row>
   <Row>
    <Cell>4353</Cell>
    <Cell>1</Cell>
    <Cell>2</Cell>
    <Cell>1</Cell>
   </Row>
   <Row>
    <Cell>4354</Cell>
    <Cell>1</Cell>
    <Cell>2</Cell>
    <Cell>1</Cell>
   </Row>
   <Row>
    <Cell>4355</Cell>
    <Cell>1</Cell>
    <Cell>2</Cell>
    <Cell>1</Cell>
   </Row>
   <Row>
    <Cell>4356</Cell>
    <Cell>1</Cell>
    <Cell>2</Cell>
    <Cell>1</Cell>
   </Row>
   <Row>
    <Cell>4357</Cell>
    <Cell>1</Cell>
    <Cell>2</Cell>
    <Cell>1</Cell>
   </Row>
   <Row>
    <Cell>4358</Cell>
    <Cell>1</Cell>
    <Cell>2</Cell>
    <Cell>1</Cell>
   </Row>
   <Row>
    <Cell>4359</Cell>
    <Cell>1</Cell>
    <Cell>2</Cell>
    <Cell>1</Cell>
   </Row>
   <Row>
    <Cell>4360</Cell>
    <Cell>1</Cell>
    <Cell>2</Cell>
    <Cell>1</Cell>
   </Row>
   <Row>
    <Cell>4361</Cell>
    <Cell>1</Cell>
    <Cell>2</Cell>
    <Cell>1</Cell>
   </Row>
   <Row>
    <Cell>4362</Cell>
    <Cell>1</Cell>
    <Cell>2</Cell>
    <Cell>1</Cell>
   </Row>
   <Row>
    <Cell>4363</Cell>
    <Cell>1</Cell>
    <Cell>2</Cell>
    <Cell>1</Cell>
   </Row>
   <Row>
    <Cell>4364</Cell>
    <Cell>1</Cell>
    <Cell>2</Cell>
    <Cell>1</Cell>
   </Row>
   <Row>
    <Cell>4365</Cell>
    <Cell>1</Cell>
    <Cell>2</Cell>
    <Cell>1</Cell>
   </Row>
   <Row>
    <Cell>4366</Cell>
    <Cell>1</Cell>
    <Cell>2</Cell>
    <Cell>1</Cell>
   </Row>
   <Row>
    <Cell>4367</Cell>
    <Cell>1</Cell>
    <Cell>2</Cell>
    <Cell>1</Cell>
   </Row>
   <Row>
    <Cell>4368</Cell>
    <Cell>1</Cell>
    <Cell>2</Cell>
    <Cell>1</Cell>
   </Row>
   <Row>
    <Cell>4369</Cell>
    <Cell>1</Cell>
    <Cell>2</Cell>
    <Cell>1</Cell>
   </Row>
   <Row>
    <Cell>4370</Cell>
    <Cell>1</Cell>
    <Cell>2</Cell>
    <Cell>1</Cell>
   </Row>
   <Row>
    <Cell>4371</Cell>
    <Cell>1</Cell>
    <Cell>2</Cell>
    <Cell>1</Cell>
   </Row>
   <Row>
    <Cell>4372</Cell>
    <Cell>1</Cell>
    <Cell>2</Cell>
    <Cell>1</Cell>
   </Row>
   <Row>
    <Cell>4373</Cell>
    <Cell>1</Cell>
    <Cell>2</Cell>
    <Cell>1</Cell>
   </Row>
   <Row>
    <Cell>4374</Cell>
    <Cell>1</Cell>
    <Cell>2</Cell>
    <Cell>1</Cell>
   </Row>
   <Row>
    <Cell>4375</Cell>
    <Cell>1</Cell>
    <Cell>2</Cell>
    <Cell>1</Cell>
   </Row>
   <Row>
    <Cell>4376</Cell>
    <Cell>1</Cell>
    <Cell>2</Cell>
    <Cell>1</Cell>
   </Row>
   <Row>
    <Cell>4377</Cell>
    <Cell>1</Cell>
    <Cell>2</Cell>
    <Cell>1</Cell>
   </Row>
   <Row>
    <Cell>4378</Cell>
    <Cell>1</Cell>
    <Cell>2</Cell>
    <Cell>1</Cell>
   </Row>
   <Row>
    <Cell>4379</Cell>
    <Cell>1</Cell>
    <Cell>2</Cell>
    <Cell>1</Cell>
   </Row>
   <Row>
    <Cell>4380</Cell>
    <Cell>1</Cell>
    <Cell>2</Cell>
    <Cell>1</Cell>
   </Row>
   <Row>
    <Cell>4381</Cell>
    <Cell>1</Cell>
    <Cell>2</Cell>
    <Cell>1</Cell>
   </Row>
   <Row>
    <Cell>4382</Cell>
    <Cell>1</Cell>
    <Cell>2</Cell>
    <Cell>1</Cell>
   </Row>
   <Row>
    <Cell>4383</Cell>
    <Cell>1</Cell>
    <Cell>2</Cell>
    <Cell>1</Cell>
   </Row>
   <Row>
    <Cell>4384</Cell>
    <Cell>1</Cell>
    <Cell>2</Cell>
    <Cell>1</Cell>
   </Row>
   <Row>
    <Cell>4385</Cell>
    <Cell>1</Cell>
    <Cell>2</Cell>
    <Cell>1</Cell>
   </Row>
   <Row>
    <Cell>4386</Cell>
    <Cell>1</Cell>
    <Cell>2</Cell>
    <Cell>1</Cell>
   </Row>
   <Row>
    <Cell>4387</Cell>
    <Cell>1</Cell>
    <Cell>2</Cell>
    <Cell>1</Cell>
   </Row>
   <Row>
    <Cell>4388</Cell>
    <Cell>1</Cell>
    <Cell>2</Cell>
    <Cell>1</Cell>
   </Row>
   <Row>
    <Cell>4389</Cell>
    <Cell>1</Cell>
    <Cell>2</Cell>
    <Cell>1</Cell>
   </Row>
   <Row>
    <Cell>4390</Cell>
    <Cell>1</Cell>
    <Cell>2</Cell>
    <Cell>1</Cell>
   </Row>
   <Row>
    <Cell>4391</Cell>
    <Cell>1</Cell>
    <Cell>2</Cell>
    <Cell>1</Cell>
   </Row>
   <Row>
    <Cell>4392</Cell>
    <Cell>1</Cell>
    <Cell>2</Cell>
    <Cell>1</Cell>
   </Row>
   <Row>
    <Cell>4393</Cell>
    <Cell>1</Cell>
    <Cell>2</Cell>
    <Cell>1</Cell>
   </Row>
   <Row>
    <Cell>4394</Cell>
    <Cell>1</Cell>
    <Cell>2</Cell>
    <Cell>1</Cell>
   </Row>
   <Row>
    <Cell>4395</Cell>
    <Cell>1</Cell>
    <Cell>2</Cell>
    <Cell>1</Cell>
   </Row>
   <Row>
    <Cell>4396</Cell>
    <Cell>1</Cell>
    <Cell>2</Cell>
    <Cell>1</Cell>
   </Row>
   <Row>
    <Cell>4397</Cell>
    <Cell>1</Cell>
    <Cell>2</Cell>
    <Cell>1</Cell>
   </Row>
   <Row>
    <Cell>4398</Cell>
    <Cell>1</Cell>
    <Cell>2</Cell>
    <Cell>1</Cell>
   </Row>
   <Row>
    <Cell>4399</Cell>
    <Cell>1</Cell>
    <Cell>2</Cell>
    <Cell>1</Cell>
   </Row>
   <Row>
    <Cell>4400</Cell>
    <Cell>1</Cell>
    <Cell>2</Cell>
    <Cell>1</Cell>
   </Row>
   <Row>
    <Cell>4401</Cell>
    <Cell>1</Cell>
    <Cell>2</Cell>
    <Cell>1</Cell>
   </Row>
   <Row>
    <Cell>4402</Cell>
    <Cell>1</Cell>
    <Cell>2</Cell>
    <Cell>1</Cell>
   </Row>
   <Row>
    <Cell>4403</Cell>
    <Cell>1</Cell>
    <Cell>2</Cell>
    <Cell>1</Cell>
   </Row>
   <Row>
    <Cell>4404</Cell>
    <Cell>1</Cell>
    <Cell>2</Cell>
    <Cell>1</Cell>
   </Row>
   <Row>
    <Cell>4405</Cell>
    <Cell>1</Cell>
    <Cell>2</Cell>
    <Cell>1</Cell>
   </Row>
   <Row>
    <Cell>4406</Cell>
    <Cell>1</Cell>
    <Cell>2</Cell>
    <Cell>1</Cell>
   </Row>
   <Row>
    <Cell>4407</Cell>
    <Cell>1</Cell>
    <Cell>2</Cell>
    <Cell>1</Cell>
   </Row>
   <Row>
    <Cell>4408</Cell>
    <Cell>1</Cell>
    <Cell>2</Cell>
    <Cell>1</Cell>
   </Row>
   <Row>
    <Cell>4409</Cell>
    <Cell>1</Cell>
    <Cell>2</Cell>
    <Cell>1</Cell>
   </Row>
   <Row>
    <Cell>4410</Cell>
    <Cell>1</Cell>
    <Cell>2</Cell>
    <Cell>1</Cell>
   </Row>
   <Row>
    <Cell>4411</Cell>
    <Cell>1</Cell>
    <Cell>2</Cell>
    <Cell>1</Cell>
   </Row>
   <Row>
    <Cell>4412</Cell>
    <Cell>1</Cell>
    <Cell>2</Cell>
    <Cell>1</Cell>
   </Row>
   <Row>
    <Cell>4413</Cell>
    <Cell>1</Cell>
    <Cell>2</Cell>
    <Cell>1</Cell>
   </Row>
   <Row>
    <Cell>4414</Cell>
    <Cell>1</Cell>
    <Cell>2</Cell>
    <Cell>1</Cell>
   </Row>
   <Row>
    <Cell>4415</Cell>
    <Cell>1</Cell>
    <Cell>2</Cell>
    <Cell>1</Cell>
   </Row>
   <Row>
    <Cell>4416</Cell>
    <Cell>1</Cell>
    <Cell>2</Cell>
    <Cell>1</Cell>
   </Row>
   <Row>
    <Cell>4417</Cell>
    <Cell>1</Cell>
    <Cell>2</Cell>
    <Cell>1</Cell>
   </Row>
   <Row>
    <Cell>4418</Cell>
    <Cell>1</Cell>
    <Cell>2</Cell>
    <Cell>1</Cell>
   </Row>
   <Row>
    <Cell>4419</Cell>
    <Cell>1</Cell>
    <Cell>2</Cell>
    <Cell>1</Cell>
   </Row>
   <Row>
    <Cell>4420</Cell>
    <Cell>1</Cell>
    <Cell>2</Cell>
    <Cell>1</Cell>
   </Row>
   <Row>
    <Cell>4421</Cell>
    <Cell>1</Cell>
    <Cell>2</Cell>
    <Cell>1</Cell>
   </Row>
   <Row>
    <Cell>4422</Cell>
    <Cell>1</Cell>
    <Cell>2</Cell>
    <Cell>1</Cell>
   </Row>
   <Row>
    <Cell>4423</Cell>
    <Cell>1</Cell>
    <Cell>2</Cell>
    <Cell>1</Cell>
   </Row>
   <Row>
    <Cell>4424</Cell>
    <Cell>1</Cell>
    <Cell>2</Cell>
    <Cell>1</Cell>
   </Row>
   <Row>
    <Cell>4425</Cell>
    <Cell>1</Cell>
    <Cell>2</Cell>
    <Cell>1</Cell>
   </Row>
   <Row>
    <Cell>4426</Cell>
    <Cell>1</Cell>
    <Cell>2</Cell>
    <Cell>1</Cell>
   </Row>
   <Row>
    <Cell>4427</Cell>
    <Cell>1</Cell>
    <Cell>2</Cell>
    <Cell>1</Cell>
   </Row>
   <Row>
    <Cell>4428</Cell>
    <Cell>1</Cell>
    <Cell>2</Cell>
    <Cell>1</Cell>
   </Row>
   <Row>
    <Cell>4429</Cell>
    <Cell>1</Cell>
    <Cell>2</Cell>
    <Cell>1</Cell>
   </Row>
   <Row>
    <Cell>4430</Cell>
    <Cell>1</Cell>
    <Cell>2</Cell>
    <Cell>1</Cell>
   </Row>
   <Row>
    <Cell>4431</Cell>
    <Cell>1</Cell>
    <Cell>2</Cell>
    <Cell>1</Cell>
   </Row>
   <Row>
    <Cell>4432</Cell>
    <Cell>1</Cell>
    <Cell>2</Cell>
    <Cell>1</Cell>
   </Row>
   <Row>
    <Cell>4433</Cell>
    <Cell>1</Cell>
    <Cell>2</Cell>
    <Cell>1</Cell>
   </Row>
   <Row>
    <Cell>4434</Cell>
    <Cell>1</Cell>
    <Cell>2</Cell>
    <Cell>1</Cell>
   </Row>
   <Row>
    <Cell>4435</Cell>
    <Cell>1</Cell>
    <Cell>2</Cell>
    <Cell>1</Cell>
   </Row>
   <Row>
    <Cell>4436</Cell>
    <Cell>1</Cell>
    <Cell>2</Cell>
    <Cell>1</Cell>
   </Row>
   <Row>
    <Cell>4437</Cell>
    <Cell>1</Cell>
    <Cell>2</Cell>
    <Cell>1</Cell>
   </Row>
   <Row>
    <Cell>4438</Cell>
    <Cell>1</Cell>
    <Cell>2</Cell>
    <Cell>1</Cell>
   </Row>
   <Row>
    <Cell>4439</Cell>
    <Cell>1</Cell>
    <Cell>2</Cell>
    <Cell>1</Cell>
   </Row>
   <Row>
    <Cell>4440</Cell>
    <Cell>1</Cell>
    <Cell>2</Cell>
    <Cell>1</Cell>
   </Row>
   <Row>
    <Cell>4441</Cell>
    <Cell>1</Cell>
    <Cell>2</Cell>
    <Cell>1</Cell>
   </Row>
   <Row>
    <Cell>4442</Cell>
    <Cell>1</Cell>
    <Cell>2</Cell>
    <Cell>1</Cell>
   </Row>
   <Row>
    <Cell>4443</Cell>
    <Cell>1</Cell>
    <Cell>2</Cell>
    <Cell>1</Cell>
   </Row>
   <Row>
    <Cell>4444</Cell>
    <Cell>1</Cell>
    <Cell>2</Cell>
    <Cell>1</Cell>
   </Row>
   <Row>
    <Cell>4445</Cell>
    <Cell>1</Cell>
    <Cell>2</Cell>
    <Cell>1</Cell>
   </Row>
   <Row>
    <Cell>4446</Cell>
    <Cell>1</Cell>
    <Cell>2</Cell>
    <Cell>1</Cell>
   </Row>
   <Row>
    <Cell>4447</Cell>
    <Cell>1</Cell>
    <Cell>2</Cell>
    <Cell>1</Cell>
   </Row>
   <Row>
    <Cell>4448</Cell>
    <Cell>1</Cell>
    <Cell>2</Cell>
    <Cell>1</Cell>
   </Row>
   <Row>
    <Cell>4449</Cell>
    <Cell>1</Cell>
    <Cell>2</Cell>
    <Cell>1</Cell>
   </Row>
   <Row>
    <Cell>4450</Cell>
    <Cell>1</Cell>
    <Cell>2</Cell>
    <Cell>1</Cell>
   </Row>
   <Row>
    <Cell>4451</Cell>
    <Cell>1</Cell>
    <Cell>2</Cell>
    <Cell>1</Cell>
   </Row>
   <Row>
    <Cell>4452</Cell>
    <Cell>1</Cell>
    <Cell>2</Cell>
    <Cell>1</Cell>
   </Row>
   <Row>
    <Cell>4453</Cell>
    <Cell>1</Cell>
    <Cell>2</Cell>
    <Cell>1</Cell>
   </Row>
   <Row>
    <Cell>4454</Cell>
    <Cell>1</Cell>
    <Cell>2</Cell>
    <Cell>1</Cell>
   </Row>
   <Row>
    <Cell>4455</Cell>
    <Cell>1</Cell>
    <Cell>2</Cell>
    <Cell>1</Cell>
   </Row>
   <Row>
    <Cell>4456</Cell>
    <Cell>1</Cell>
    <Cell>2</Cell>
    <Cell>1</Cell>
   </Row>
   <Row>
    <Cell>4457</Cell>
    <Cell>1</Cell>
    <Cell>2</Cell>
    <Cell>1</Cell>
   </Row>
   <Row>
    <Cell>4458</Cell>
    <Cell>1</Cell>
    <Cell>2</Cell>
    <Cell>1</Cell>
   </Row>
   <Row>
    <Cell>4459</Cell>
    <Cell>1</Cell>
    <Cell>2</Cell>
    <Cell>1</Cell>
   </Row>
   <Row>
    <Cell>4460</Cell>
    <Cell>1</Cell>
    <Cell>2</Cell>
    <Cell>1</Cell>
   </Row>
   <Row>
    <Cell>4461</Cell>
    <Cell>1</Cell>
    <Cell>2</Cell>
    <Cell>1</Cell>
   </Row>
   <Row>
    <Cell>4462</Cell>
    <Cell>1</Cell>
    <Cell>2</Cell>
    <Cell>1</Cell>
   </Row>
   <Row>
    <Cell>4463</Cell>
    <Cell>1</Cell>
    <Cell>2</Cell>
    <Cell>1</Cell>
   </Row>
   <Row>
    <Cell>4464</Cell>
    <Cell>1</Cell>
    <Cell>2</Cell>
    <Cell>1</Cell>
   </Row>
   <Row>
    <Cell>4465</Cell>
    <Cell>1</Cell>
    <Cell>2</Cell>
    <Cell>1</Cell>
   </Row>
   <Row>
    <Cell>4466</Cell>
    <Cell>1</Cell>
    <Cell>2</Cell>
    <Cell>1</Cell>
   </Row>
   <Row>
    <Cell>4467</Cell>
    <Cell>1</Cell>
    <Cell>2</Cell>
    <Cell>1</Cell>
   </Row>
   <Row>
    <Cell>4468</Cell>
    <Cell>1</Cell>
    <Cell>2</Cell>
    <Cell>1</Cell>
   </Row>
   <Row>
    <Cell>4469</Cell>
    <Cell>1</Cell>
    <Cell>2</Cell>
    <Cell>1</Cell>
   </Row>
   <Row>
    <Cell>4470</Cell>
    <Cell>1</Cell>
    <Cell>2</Cell>
    <Cell>1</Cell>
   </Row>
   <Row>
    <Cell>4471</Cell>
    <Cell>1</Cell>
    <Cell>2</Cell>
    <Cell>1</Cell>
   </Row>
   <Row>
    <Cell>4472</Cell>
    <Cell>1</Cell>
    <Cell>2</Cell>
    <Cell>1</Cell>
   </Row>
   <Row>
    <Cell>4473</Cell>
    <Cell>1</Cell>
    <Cell>2</Cell>
    <Cell>1</Cell>
   </Row>
   <Row>
    <Cell>4474</Cell>
    <Cell>1</Cell>
    <Cell>2</Cell>
    <Cell>1</Cell>
   </Row>
   <Row>
    <Cell>4475</Cell>
    <Cell>1</Cell>
    <Cell>2</Cell>
    <Cell>1</Cell>
   </Row>
   <Row>
    <Cell>4476</Cell>
    <Cell>1</Cell>
    <Cell>2</Cell>
    <Cell>1</Cell>
   </Row>
   <Row>
    <Cell>4477</Cell>
    <Cell>1</Cell>
    <Cell>2</Cell>
    <Cell>1</Cell>
   </Row>
   <Row>
    <Cell>4478</Cell>
    <Cell>1</Cell>
    <Cell>2</Cell>
    <Cell>1</Cell>
   </Row>
   <Row>
    <Cell>4479</Cell>
    <Cell>1</Cell>
    <Cell>2</Cell>
    <Cell>1</Cell>
   </Row>
   <Row>
    <Cell>4480</Cell>
    <Cell>1</Cell>
    <Cell>2</Cell>
    <Cell>1</Cell>
   </Row>
   <Row>
    <Cell>4481</Cell>
    <Cell>1</Cell>
    <Cell>2</Cell>
    <Cell>1</Cell>
   </Row>
   <Row>
    <Cell>4482</Cell>
    <Cell>1</Cell>
    <Cell>2</Cell>
    <Cell>1</Cell>
   </Row>
   <Row>
    <Cell>4483</Cell>
    <Cell>1</Cell>
    <Cell>2</Cell>
    <Cell>1</Cell>
   </Row>
   <Row>
    <Cell>4484</Cell>
    <Cell>1</Cell>
    <Cell>2</Cell>
    <Cell>1</Cell>
   </Row>
   <Row>
    <Cell>4485</Cell>
    <Cell>1</Cell>
    <Cell>2</Cell>
    <Cell>1</Cell>
   </Row>
   <Row>
    <Cell>4486</Cell>
    <Cell>1</Cell>
    <Cell>2</Cell>
    <Cell>1</Cell>
   </Row>
   <Row>
    <Cell>4487</Cell>
    <Cell>1</Cell>
    <Cell>2</Cell>
    <Cell>1</Cell>
   </Row>
   <Row>
    <Cell>4488</Cell>
    <Cell>1</Cell>
    <Cell>2</Cell>
    <Cell>1</Cell>
   </Row>
   <Row>
    <Cell>4489</Cell>
    <Cell>1</Cell>
    <Cell>2</Cell>
    <Cell>1</Cell>
   </Row>
   <Row>
    <Cell>4490</Cell>
    <Cell>1</Cell>
    <Cell>2</Cell>
    <Cell>1</Cell>
   </Row>
   <Row>
    <Cell>4491</Cell>
    <Cell>1</Cell>
    <Cell>2</Cell>
    <Cell>1</Cell>
   </Row>
   <Row>
    <Cell>4492</Cell>
    <Cell>1</Cell>
    <Cell>2</Cell>
    <Cell>1</Cell>
   </Row>
   <Row>
    <Cell>4493</Cell>
    <Cell>1</Cell>
    <Cell>2</Cell>
    <Cell>1</Cell>
   </Row>
   <Row>
    <Cell>4494</Cell>
    <Cell>1</Cell>
    <Cell>2</Cell>
    <Cell>1</Cell>
   </Row>
   <Row>
    <Cell>4495</Cell>
    <Cell>1</Cell>
    <Cell>2</Cell>
    <Cell>1</Cell>
   </Row>
   <Row>
    <Cell>4496</Cell>
    <Cell>1</Cell>
    <Cell>2</Cell>
    <Cell>1</Cell>
   </Row>
   <Row>
    <Cell>4497</Cell>
    <Cell>1</Cell>
    <Cell>2</Cell>
    <Cell>1</Cell>
   </Row>
   <Row>
    <Cell>4498</Cell>
    <Cell>1</Cell>
    <Cell>2</Cell>
    <Cell>1</Cell>
   </Row>
   <Row>
    <Cell>4499</Cell>
    <Cell>1</Cell>
    <Cell>2</Cell>
    <Cell>1</Cell>
   </Row>
   <Row>
    <Cell>4500</Cell>
    <Cell>1</Cell>
    <Cell>2</Cell>
    <Cell>1</Cell>
   </Row>
   <Row>
    <Cell>4501</Cell>
    <Cell>1</Cell>
    <Cell>2</Cell>
    <Cell>1</Cell>
   </Row>
   <Row>
    <Cell>4502</Cell>
    <Cell>1</Cell>
    <Cell>2</Cell>
    <Cell>1</Cell>
   </Row>
   <Row>
    <Cell>4503</Cell>
    <Cell>1</Cell>
    <Cell>2</Cell>
    <Cell>1</Cell>
   </Row>
   <Row>
    <Cell>4504</Cell>
    <Cell>1</Cell>
    <Cell>2</Cell>
    <Cell>1</Cell>
   </Row>
   <Row>
    <Cell>4505</Cell>
    <Cell>1</Cell>
    <Cell>2</Cell>
    <Cell>1</Cell>
   </Row>
   <Row>
    <Cell>4506</Cell>
    <Cell>1</Cell>
    <Cell>2</Cell>
    <Cell>1</Cell>
   </Row>
   <Row>
    <Cell>4507</Cell>
    <Cell>1</Cell>
    <Cell>2</Cell>
    <Cell>1</Cell>
   </Row>
   <Row>
    <Cell>4508</Cell>
    <Cell>1</Cell>
    <Cell>2</Cell>
    <Cell>1</Cell>
   </Row>
   <Row>
    <Cell>4509</Cell>
    <Cell>1</Cell>
    <Cell>2</Cell>
    <Cell>1</Cell>
   </Row>
   <Row>
    <Cell>4510</Cell>
    <Cell>1</Cell>
    <Cell>2</Cell>
    <Cell>1</Cell>
   </Row>
   <Row>
    <Cell>4511</Cell>
    <Cell>1</Cell>
    <Cell>2</Cell>
    <Cell>1</Cell>
   </Row>
   <Row>
    <Cell>4512</Cell>
    <Cell>1</Cell>
    <Cell>2</Cell>
    <Cell>1</Cell>
   </Row>
   <Row>
    <Cell>4513</Cell>
    <Cell>1</Cell>
    <Cell>2</Cell>
    <Cell>1</Cell>
   </Row>
   <Row>
    <Cell>4514</Cell>
    <Cell>1</Cell>
    <Cell>2</Cell>
    <Cell>1</Cell>
   </Row>
   <Row>
    <Cell>4515</Cell>
    <Cell>1</Cell>
    <Cell>2</Cell>
    <Cell>1</Cell>
   </Row>
   <Row>
    <Cell>4516</Cell>
    <Cell>1</Cell>
    <Cell>2</Cell>
    <Cell>1</Cell>
   </Row>
   <Row>
    <Cell>4517</Cell>
    <Cell>1</Cell>
    <Cell>2</Cell>
    <Cell>1</Cell>
   </Row>
   <Row>
    <Cell>4518</Cell>
    <Cell>1</Cell>
    <Cell>2</Cell>
    <Cell>1</Cell>
   </Row>
   <Row>
    <Cell>4519</Cell>
    <Cell>1</Cell>
    <Cell>2</Cell>
    <Cell>1</Cell>
   </Row>
   <Row>
    <Cell>4520</Cell>
    <Cell>1</Cell>
    <Cell>2</Cell>
    <Cell>1</Cell>
   </Row>
   <Row>
    <Cell>4521</Cell>
    <Cell>1</Cell>
    <Cell>2</Cell>
    <Cell>1</Cell>
   </Row>
   <Row>
    <Cell>4522</Cell>
    <Cell>1</Cell>
    <Cell>2</Cell>
    <Cell>1</Cell>
   </Row>
   <Row>
    <Cell>4523</Cell>
    <Cell>1</Cell>
    <Cell>2</Cell>
    <Cell>1</Cell>
   </Row>
   <Row>
    <Cell>4524</Cell>
    <Cell>1</Cell>
    <Cell>2</Cell>
    <Cell>1</Cell>
   </Row>
   <Row>
    <Cell>4525</Cell>
    <Cell>1</Cell>
    <Cell>2</Cell>
    <Cell>1</Cell>
   </Row>
   <Row>
    <Cell>4526</Cell>
    <Cell>1</Cell>
    <Cell>2</Cell>
    <Cell>1</Cell>
   </Row>
   <Row>
    <Cell>4527</Cell>
    <Cell>1</Cell>
    <Cell>2</Cell>
    <Cell>1</Cell>
   </Row>
   <Row>
    <Cell>4528</Cell>
    <Cell>1</Cell>
    <Cell>2</Cell>
    <Cell>1</Cell>
   </Row>
   <Row>
    <Cell>4529</Cell>
    <Cell>1</Cell>
    <Cell>2</Cell>
    <Cell>1</Cell>
   </Row>
   <Row>
    <Cell>4530</Cell>
    <Cell>1</Cell>
    <Cell>2</Cell>
    <Cell>1</Cell>
   </Row>
   <Row>
    <Cell>4531</Cell>
    <Cell>1</Cell>
    <Cell>2</Cell>
    <Cell>1</Cell>
   </Row>
   <Row>
    <Cell>4532</Cell>
    <Cell>1</Cell>
    <Cell>2</Cell>
    <Cell>1</Cell>
   </Row>
   <Row>
    <Cell>4533</Cell>
    <Cell>1</Cell>
    <Cell>2</Cell>
    <Cell>1</Cell>
   </Row>
   <Row>
    <Cell>4534</Cell>
    <Cell>1</Cell>
    <Cell>2</Cell>
    <Cell>1</Cell>
   </Row>
   <Row>
    <Cell>4535</Cell>
    <Cell>1</Cell>
    <Cell>2</Cell>
    <Cell>1</Cell>
   </Row>
   <Row>
    <Cell>4536</Cell>
    <Cell>1</Cell>
    <Cell>2</Cell>
    <Cell>1</Cell>
   </Row>
   <Row>
    <Cell>4537</Cell>
    <Cell>1</Cell>
    <Cell>2</Cell>
    <Cell>1</Cell>
   </Row>
   <Row>
    <Cell>4538</Cell>
    <Cell>1</Cell>
    <Cell>2</Cell>
    <Cell>1</Cell>
   </Row>
   <Row>
    <Cell>4539</Cell>
    <Cell>1</Cell>
    <Cell>2</Cell>
    <Cell>1</Cell>
   </Row>
   <Row>
    <Cell>4540</Cell>
    <Cell>1</Cell>
    <Cell>2</Cell>
    <Cell>1</Cell>
   </Row>
   <Row>
    <Cell>4541</Cell>
    <Cell>1</Cell>
    <Cell>2</Cell>
    <Cell>1</Cell>
   </Row>
   <Row>
    <Cell>4542</Cell>
    <Cell>1</Cell>
    <Cell>2</Cell>
    <Cell>1</Cell>
   </Row>
   <Row>
    <Cell>4543</Cell>
    <Cell>1</Cell>
    <Cell>2</Cell>
    <Cell>1</Cell>
   </Row>
   <Row>
    <Cell>4544</Cell>
    <Cell>1</Cell>
    <Cell>2</Cell>
    <Cell>1</Cell>
   </Row>
   <Row>
    <Cell>4545</Cell>
    <Cell>1</Cell>
    <Cell>2</Cell>
    <Cell>1</Cell>
   </Row>
   <Row>
    <Cell>4546</Cell>
    <Cell>1</Cell>
    <Cell>2</Cell>
    <Cell>1</Cell>
   </Row>
   <Row>
    <Cell>4547</Cell>
    <Cell>1</Cell>
    <Cell>2</Cell>
    <Cell>1</Cell>
   </Row>
   <Row>
    <Cell>4548</Cell>
    <Cell>1</Cell>
    <Cell>2</Cell>
    <Cell>1</Cell>
   </Row>
   <Row>
    <Cell>4549</Cell>
    <Cell>1</Cell>
    <Cell>2</Cell>
    <Cell>1</Cell>
   </Row>
   <Row>
    <Cell>4550</Cell>
    <Cell>1</Cell>
    <Cell>2</Cell>
    <Cell>1</Cell>
   </Row>
   <Row>
    <Cell>4551</Cell>
    <Cell>1</Cell>
    <Cell>2</Cell>
    <Cell>1</Cell>
   </Row>
   <Row>
    <Cell>4552</Cell>
    <Cell>1</Cell>
    <Cell>2</Cell>
    <Cell>1</Cell>
   </Row>
   <Row>
    <Cell>4553</Cell>
    <Cell>1</Cell>
    <Cell>2</Cell>
    <Cell>1</Cell>
   </Row>
   <Row>
    <Cell>4554</Cell>
    <Cell>1</Cell>
    <Cell>2</Cell>
    <Cell>1</Cell>
   </Row>
   <Row>
    <Cell>4555</Cell>
    <Cell>1</Cell>
    <Cell>2</Cell>
    <Cell>1</Cell>
   </Row>
   <Row>
    <Cell>4556</Cell>
    <Cell>1</Cell>
    <Cell>2</Cell>
    <Cell>1</Cell>
   </Row>
   <Row>
    <Cell>4557</Cell>
    <Cell>1</Cell>
    <Cell>2</Cell>
    <Cell>1</Cell>
   </Row>
   <Row>
    <Cell>4558</Cell>
    <Cell>1</Cell>
    <Cell>2</Cell>
    <Cell>1</Cell>
   </Row>
   <Row>
    <Cell>4559</Cell>
    <Cell>1</Cell>
    <Cell>2</Cell>
    <Cell>1</Cell>
   </Row>
   <Row>
    <Cell>4560</Cell>
    <Cell>1</Cell>
    <Cell>2</Cell>
    <Cell>1</Cell>
   </Row>
   <Row>
    <Cell>4561</Cell>
    <Cell>1</Cell>
    <Cell>2</Cell>
    <Cell>1</Cell>
   </Row>
   <Row>
    <Cell>4562</Cell>
    <Cell>1</Cell>
    <Cell>2</Cell>
    <Cell>1</Cell>
   </Row>
   <Row>
    <Cell>4563</Cell>
    <Cell>1</Cell>
    <Cell>2</Cell>
    <Cell>1</Cell>
   </Row>
   <Row>
    <Cell>4564</Cell>
    <Cell>1</Cell>
    <Cell>2</Cell>
    <Cell>1</Cell>
   </Row>
   <Row>
    <Cell>4565</Cell>
    <Cell>1</Cell>
    <Cell>2</Cell>
    <Cell>1</Cell>
   </Row>
   <Row>
    <Cell>4566</Cell>
    <Cell>1</Cell>
    <Cell>2</Cell>
    <Cell>1</Cell>
   </Row>
   <Row>
    <Cell>4567</Cell>
    <Cell>1</Cell>
    <Cell>2</Cell>
    <Cell>1</Cell>
   </Row>
   <Row>
    <Cell>4568</Cell>
    <Cell>1</Cell>
    <Cell>2</Cell>
    <Cell>1</Cell>
   </Row>
   <Row>
    <Cell>4569</Cell>
    <Cell>1</Cell>
    <Cell>2</Cell>
    <Cell>1</Cell>
   </Row>
   <Row>
    <Cell>4570</Cell>
    <Cell>1</Cell>
    <Cell>2</Cell>
    <Cell>1</Cell>
   </Row>
   <Row>
    <Cell>4571</Cell>
    <Cell>1</Cell>
    <Cell>2</Cell>
    <Cell>1</Cell>
   </Row>
   <Row>
    <Cell>4572</Cell>
    <Cell>1</Cell>
    <Cell>2</Cell>
    <Cell>1</Cell>
   </Row>
   <Row>
    <Cell>4573</Cell>
    <Cell>1</Cell>
    <Cell>2</Cell>
    <Cell>1</Cell>
   </Row>
   <Row>
    <Cell>4574</Cell>
    <Cell>1</Cell>
    <Cell>2</Cell>
    <Cell>1</Cell>
   </Row>
   <Row>
    <Cell>4575</Cell>
    <Cell>1</Cell>
    <Cell>2</Cell>
    <Cell>1</Cell>
   </Row>
   <Row>
    <Cell>4576</Cell>
    <Cell>1</Cell>
    <Cell>2</Cell>
    <Cell>1</Cell>
   </Row>
   <Row>
    <Cell>4577</Cell>
    <Cell>1</Cell>
    <Cell>2</Cell>
    <Cell>1</Cell>
   </Row>
   <Row>
    <Cell>4578</Cell>
    <Cell>1</Cell>
    <Cell>2</Cell>
    <Cell>1</Cell>
   </Row>
   <Row>
    <Cell>4579</Cell>
    <Cell>1</Cell>
    <Cell>2</Cell>
    <Cell>1</Cell>
   </Row>
   <Row>
    <Cell>4580</Cell>
    <Cell>1</Cell>
    <Cell>2</Cell>
    <Cell>1</Cell>
   </Row>
   <Row>
    <Cell>4581</Cell>
    <Cell>1</Cell>
    <Cell>2</Cell>
    <Cell>1</Cell>
   </Row>
   <Row>
    <Cell>4582</Cell>
    <Cell>1</Cell>
    <Cell>2</Cell>
    <Cell>1</Cell>
   </Row>
   <Row>
    <Cell>4583</Cell>
    <Cell>1</Cell>
    <Cell>2</Cell>
    <Cell>1</Cell>
   </Row>
   <Row>
    <Cell>4584</Cell>
    <Cell>1</Cell>
    <Cell>2</Cell>
    <Cell>1</Cell>
   </Row>
   <Row>
    <Cell>4585</Cell>
    <Cell>1</Cell>
    <Cell>2</Cell>
    <Cell>1</Cell>
   </Row>
   <Row>
    <Cell>4586</Cell>
    <Cell>1</Cell>
    <Cell>2</Cell>
    <Cell>1</Cell>
   </Row>
   <Row>
    <Cell>4587</Cell>
    <Cell>1</Cell>
    <Cell>2</Cell>
    <Cell>1</Cell>
   </Row>
   <Row>
    <Cell>4588</Cell>
    <Cell>1</Cell>
    <Cell>2</Cell>
    <Cell>1</Cell>
   </Row>
   <Row>
    <Cell>4589</Cell>
    <Cell>1</Cell>
    <Cell>2</Cell>
    <Cell>1</Cell>
   </Row>
   <Row>
    <Cell>4590</Cell>
    <Cell>1</Cell>
    <Cell>2</Cell>
    <Cell>1</Cell>
   </Row>
   <Row>
    <Cell>4591</Cell>
    <Cell>1</Cell>
    <Cell>2</Cell>
    <Cell>1</Cell>
   </Row>
   <Row>
    <Cell>4592</Cell>
    <Cell>1</Cell>
    <Cell>2</Cell>
    <Cell>1</Cell>
   </Row>
   <Row>
    <Cell>4593</Cell>
    <Cell>1</Cell>
    <Cell>2</Cell>
    <Cell>1</Cell>
   </Row>
   <Row>
    <Cell>4594</Cell>
    <Cell>1</Cell>
    <Cell>2</Cell>
    <Cell>1</Cell>
   </Row>
   <Row>
    <Cell>4595</Cell>
    <Cell>1</Cell>
    <Cell>2</Cell>
    <Cell>1</Cell>
   </Row>
   <Row>
    <Cell>4596</Cell>
    <Cell>1</Cell>
    <Cell>2</Cell>
    <Cell>1</Cell>
   </Row>
   <Row>
    <Cell>4597</Cell>
    <Cell>1</Cell>
    <Cell>2</Cell>
    <Cell>1</Cell>
   </Row>
   <Row>
    <Cell>4598</Cell>
    <Cell>1</Cell>
    <Cell>2</Cell>
    <Cell>1</Cell>
   </Row>
   <Row>
    <Cell>4599</Cell>
    <Cell>1</Cell>
    <Cell>2</Cell>
    <Cell>1</Cell>
   </Row>
   <Row>
    <Cell>4600</Cell>
    <Cell>1</Cell>
    <Cell>2</Cell>
    <Cell>1</Cell>
   </Row>
   <Row>
    <Cell>4601</Cell>
    <Cell>1</Cell>
    <Cell>2</Cell>
    <Cell>1</Cell>
   </Row>
   <Row>
    <Cell>4602</Cell>
    <Cell>1</Cell>
    <Cell>2</Cell>
    <Cell>1</Cell>
   </Row>
   <Row>
    <Cell>4603</Cell>
    <Cell>1</Cell>
    <Cell>2</Cell>
    <Cell>1</Cell>
   </Row>
   <Row>
    <Cell>4604</Cell>
    <Cell>1</Cell>
    <Cell>2</Cell>
    <Cell>1</Cell>
   </Row>
   <Row>
    <Cell>4605</Cell>
    <Cell>1</Cell>
    <Cell>2</Cell>
    <Cell>1</Cell>
   </Row>
   <Row>
    <Cell>4606</Cell>
    <Cell>1</Cell>
    <Cell>2</Cell>
    <Cell>1</Cell>
   </Row>
   <Row>
    <Cell>4607</Cell>
    <Cell>1</Cell>
    <Cell>2</Cell>
    <Cell>1</Cell>
   </Row>
   <Row>
    <Cell>4608</Cell>
    <Cell>1</Cell>
    <Cell>2</Cell>
    <Cell>1</Cell>
   </Row>
   <Row>
    <Cell>4609</Cell>
    <Cell>1</Cell>
    <Cell>2</Cell>
    <Cell>1</Cell>
   </Row>
   <Row>
    <Cell>4610</Cell>
    <Cell>1</Cell>
    <Cell>2</Cell>
    <Cell>1</Cell>
   </Row>
   <Row>
    <Cell>4611</Cell>
    <Cell>1</Cell>
    <Cell>2</Cell>
    <Cell>1</Cell>
   </Row>
   <Row>
    <Cell>4612</Cell>
    <Cell>1</Cell>
    <Cell>2</Cell>
    <Cell>1</Cell>
   </Row>
   <Row>
    <Cell>4613</Cell>
    <Cell>1</Cell>
    <Cell>2</Cell>
    <Cell>1</Cell>
   </Row>
   <Row>
    <Cell>4614</Cell>
    <Cell>1</Cell>
    <Cell>2</Cell>
    <Cell>1</Cell>
   </Row>
   <Row>
    <Cell>4615</Cell>
    <Cell>1</Cell>
    <Cell>2</Cell>
    <Cell>1</Cell>
   </Row>
   <Row>
    <Cell>4616</Cell>
    <Cell>1</Cell>
    <Cell>2</Cell>
    <Cell>1</Cell>
   </Row>
   <Row>
    <Cell>4617</Cell>
    <Cell>1</Cell>
    <Cell>2</Cell>
    <Cell>1</Cell>
   </Row>
   <Row>
    <Cell>4618</Cell>
    <Cell>1</Cell>
    <Cell>2</Cell>
    <Cell>1</Cell>
   </Row>
   <Row>
    <Cell>4619</Cell>
    <Cell>1</Cell>
    <Cell>2</Cell>
    <Cell>1</Cell>
   </Row>
   <Row>
    <Cell>4620</Cell>
    <Cell>1</Cell>
    <Cell>2</Cell>
    <Cell>1</Cell>
   </Row>
   <Row>
    <Cell>4621</Cell>
    <Cell>1</Cell>
    <Cell>2</Cell>
    <Cell>1</Cell>
   </Row>
   <Row>
    <Cell>4622</Cell>
    <Cell>1</Cell>
    <Cell>2</Cell>
    <Cell>1</Cell>
   </Row>
   <Row>
    <Cell>4623</Cell>
    <Cell>1</Cell>
    <Cell>2</Cell>
    <Cell>1</Cell>
   </Row>
   <Row>
    <Cell>4624</Cell>
    <Cell>1</Cell>
    <Cell>2</Cell>
    <Cell>1</Cell>
   </Row>
   <Row>
    <Cell>4625</Cell>
    <Cell>1</Cell>
    <Cell>2</Cell>
    <Cell>1</Cell>
   </Row>
   <Row>
    <Cell>4626</Cell>
    <Cell>1</Cell>
    <Cell>2</Cell>
    <Cell>1</Cell>
   </Row>
   <Row>
    <Cell>4627</Cell>
    <Cell>1</Cell>
    <Cell>2</Cell>
    <Cell>1</Cell>
   </Row>
   <Row>
    <Cell>4628</Cell>
    <Cell>1</Cell>
    <Cell>2</Cell>
    <Cell>1</Cell>
   </Row>
   <Row>
    <Cell>4629</Cell>
    <Cell>1</Cell>
    <Cell>2</Cell>
    <Cell>1</Cell>
   </Row>
   <Row>
    <Cell>4630</Cell>
    <Cell>1</Cell>
    <Cell>2</Cell>
    <Cell>1</Cell>
   </Row>
   <Row>
    <Cell>4631</Cell>
    <Cell>1</Cell>
    <Cell>2</Cell>
    <Cell>1</Cell>
   </Row>
   <Row>
    <Cell>4632</Cell>
    <Cell>1</Cell>
    <Cell>2</Cell>
    <Cell>1</Cell>
   </Row>
   <Row>
    <Cell>4633</Cell>
    <Cell>1</Cell>
    <Cell>2</Cell>
    <Cell>1</Cell>
   </Row>
   <Row>
    <Cell>4634</Cell>
    <Cell>1</Cell>
    <Cell>2</Cell>
    <Cell>1</Cell>
   </Row>
   <Row>
    <Cell>4635</Cell>
    <Cell>1</Cell>
    <Cell>2</Cell>
    <Cell>1</Cell>
   </Row>
   <Row>
    <Cell>4636</Cell>
    <Cell>1</Cell>
    <Cell>2</Cell>
    <Cell>1</Cell>
   </Row>
   <Row>
    <Cell>4637</Cell>
    <Cell>1</Cell>
    <Cell>2</Cell>
    <Cell>1</Cell>
   </Row>
   <Row>
    <Cell>4638</Cell>
    <Cell>1</Cell>
    <Cell>2</Cell>
    <Cell>1</Cell>
   </Row>
   <Row>
    <Cell>4639</Cell>
    <Cell>1</Cell>
    <Cell>2</Cell>
    <Cell>1</Cell>
   </Row>
   <Row>
    <Cell>4640</Cell>
    <Cell>1</Cell>
    <Cell>2</Cell>
    <Cell>1</Cell>
   </Row>
   <Row>
    <Cell>4641</Cell>
    <Cell>1</Cell>
    <Cell>2</Cell>
    <Cell>1</Cell>
   </Row>
   <Row>
    <Cell>4642</Cell>
    <Cell>1</Cell>
    <Cell>2</Cell>
    <Cell>1</Cell>
   </Row>
   <Row>
    <Cell>4643</Cell>
    <Cell>1</Cell>
    <Cell>2</Cell>
    <Cell>1</Cell>
   </Row>
   <Row>
    <Cell>4644</Cell>
    <Cell>1</Cell>
    <Cell>2</Cell>
    <Cell>1</Cell>
   </Row>
   <Row>
    <Cell>4645</Cell>
    <Cell>1</Cell>
    <Cell>2</Cell>
    <Cell>1</Cell>
   </Row>
   <Row>
    <Cell>4646</Cell>
    <Cell>1</Cell>
    <Cell>2</Cell>
    <Cell>1</Cell>
   </Row>
   <Row>
    <Cell>4647</Cell>
    <Cell>1</Cell>
    <Cell>2</Cell>
    <Cell>1</Cell>
   </Row>
   <Row>
    <Cell>4648</Cell>
    <Cell>1</Cell>
    <Cell>2</Cell>
    <Cell>1</Cell>
   </Row>
   <Row>
    <Cell>4649</Cell>
    <Cell>1</Cell>
    <Cell>2</Cell>
    <Cell>1</Cell>
   </Row>
   <Row>
    <Cell>4650</Cell>
    <Cell>1</Cell>
    <Cell>2</Cell>
    <Cell>1</Cell>
   </Row>
   <Row>
    <Cell>4651</Cell>
    <Cell>1</Cell>
    <Cell>2</Cell>
    <Cell>1</Cell>
   </Row>
   <Row>
    <Cell>4652</Cell>
    <Cell>1</Cell>
    <Cell>2</Cell>
    <Cell>1</Cell>
   </Row>
   <Row>
    <Cell>4653</Cell>
    <Cell>1</Cell>
    <Cell>2</Cell>
    <Cell>1</Cell>
   </Row>
   <Row>
    <Cell>4654</Cell>
    <Cell>1</Cell>
    <Cell>2</Cell>
    <Cell>1</Cell>
   </Row>
   <Row>
    <Cell>4655</Cell>
    <Cell>1</Cell>
    <Cell>2</Cell>
    <Cell>1</Cell>
   </Row>
   <Row>
    <Cell>4656</Cell>
    <Cell>1</Cell>
    <Cell>2</Cell>
    <Cell>1</Cell>
   </Row>
   <Row>
    <Cell>4657</Cell>
    <Cell>1</Cell>
    <Cell>2</Cell>
    <Cell>1</Cell>
   </Row>
   <Row>
    <Cell>4658</Cell>
    <Cell>1</Cell>
    <Cell>2</Cell>
    <Cell>1</Cell>
   </Row>
   <Row>
    <Cell>4659</Cell>
    <Cell>1</Cell>
    <Cell>2</Cell>
    <Cell>1</Cell>
   </Row>
   <Row>
    <Cell>4660</Cell>
    <Cell>1</Cell>
    <Cell>2</Cell>
    <Cell>1</Cell>
   </Row>
   <Row>
    <Cell>4661</Cell>
    <Cell>1</Cell>
    <Cell>2</Cell>
    <Cell>1</Cell>
   </Row>
   <Row>
    <Cell>4662</Cell>
    <Cell>1</Cell>
    <Cell>2</Cell>
    <Cell>1</Cell>
   </Row>
   <Row>
    <Cell>4663</Cell>
    <Cell>1</Cell>
    <Cell>2</Cell>
    <Cell>1</Cell>
   </Row>
   <Row>
    <Cell>4664</Cell>
    <Cell>1</Cell>
    <Cell>2</Cell>
    <Cell>1</Cell>
   </Row>
   <Row>
    <Cell>4665</Cell>
    <Cell>1</Cell>
    <Cell>2</Cell>
    <Cell>1</Cell>
   </Row>
   <Row>
    <Cell>4666</Cell>
    <Cell>1</Cell>
    <Cell>2</Cell>
    <Cell>1</Cell>
   </Row>
   <Row>
    <Cell>4667</Cell>
    <Cell>1</Cell>
    <Cell>2</Cell>
    <Cell>1</Cell>
   </Row>
   <Row>
    <Cell>4668</Cell>
    <Cell>1</Cell>
    <Cell>2</Cell>
    <Cell>1</Cell>
   </Row>
   <Row>
    <Cell>4669</Cell>
    <Cell>1</Cell>
    <Cell>2</Cell>
    <Cell>1</Cell>
   </Row>
   <Row>
    <Cell>4670</Cell>
    <Cell>1</Cell>
    <Cell>2</Cell>
    <Cell>1</Cell>
   </Row>
   <Row>
    <Cell>4671</Cell>
    <Cell>1</Cell>
    <Cell>2</Cell>
    <Cell>1</Cell>
   </Row>
   <Row>
    <Cell>4672</Cell>
    <Cell>1</Cell>
    <Cell>2</Cell>
    <Cell>1</Cell>
   </Row>
   <Row>
    <Cell>4673</Cell>
    <Cell>1</Cell>
    <Cell>2</Cell>
    <Cell>1</Cell>
   </Row>
   <Row>
    <Cell>4674</Cell>
    <Cell>1</Cell>
    <Cell>2</Cell>
    <Cell>1</Cell>
   </Row>
   <Row>
    <Cell>4675</Cell>
    <Cell>1</Cell>
    <Cell>2</Cell>
    <Cell>1</Cell>
   </Row>
   <Row>
    <Cell>4676</Cell>
    <Cell>1</Cell>
    <Cell>2</Cell>
    <Cell>1</Cell>
   </Row>
   <Row>
    <Cell>4677</Cell>
    <Cell>1</Cell>
    <Cell>2</Cell>
    <Cell>1</Cell>
   </Row>
   <Row>
    <Cell>4678</Cell>
    <Cell>1</Cell>
    <Cell>2</Cell>
    <Cell>1</Cell>
   </Row>
   <Row>
    <Cell>4679</Cell>
    <Cell>1</Cell>
    <Cell>2</Cell>
    <Cell>1</Cell>
   </Row>
   <Row>
    <Cell>4680</Cell>
    <Cell>1</Cell>
    <Cell>2</Cell>
    <Cell>1</Cell>
   </Row>
   <Row>
    <Cell>4681</Cell>
    <Cell>1</Cell>
    <Cell>2</Cell>
    <Cell>1</Cell>
   </Row>
   <Row>
    <Cell>4682</Cell>
    <Cell>1</Cell>
    <Cell>2</Cell>
    <Cell>1</Cell>
   </Row>
   <Row>
    <Cell>4683</Cell>
    <Cell>1</Cell>
    <Cell>2</Cell>
    <Cell>1</Cell>
   </Row>
   <Row>
    <Cell>4684</Cell>
    <Cell>1</Cell>
    <Cell>2</Cell>
    <Cell>1</Cell>
   </Row>
  </Table>
